awesome_monaco_FEDORKURUTS/__init__.py
awesome_monaco_FEDORKURUTS/start.py
awesome_monaco_FEDORKURUTS/brains/__init__.py
awesome_monaco_FEDORKURUTS/brains/build_data.py
awesome_monaco_FEDORKURUTS/brains/config.py
awesome_monaco_FEDORKURUTS/brains/parser.py
awesome_monaco_FEDORKURUTS/brains/report.py
awesome_monaco_FEDORKURUTS/brains/utils.py
awesome_monaco_fedorkuruts-0.0.1.dist-info/METADATA
awesome_monaco_fedorkuruts-0.0.1.dist-info/WHEEL
awesome_monaco_fedorkuruts-0.0.1.dist-info/licenses/License.mit
awesome_monaco_fedorkuruts-0.0.1.dist-info/RECORD
