Metadata-Version: 2.1
Name: awesome_monaco_FEDORKURUTS
Version: 0.0.1
Summary: Monac Studing Project
Project-URL: Homepage, https://github.com/pypa/sampleproject
Project-URL: Bug Tracker, https://github.com/pypa/sampleproject/issues
Author-email: Fedor Kuruts <fedorkuruts@gmail.com>
License-File: License.mit
Classifier: License :: OSI Approved :: MIT License
Classifier: Operating System :: OS Independent
Classifier: Programming Language :: Python :: 3
Requires-Python: >=3.10
